pubmedquery/__init__.py
pubmedquery/pubmedquery.py
pubmedquery-0.1.13.dist-info/METADATA
pubmedquery-0.1.13.dist-info/WHEEL
pubmedquery-0.1.13.dist-info/top_level.txt
pubmedquery-0.1.13.dist-info/RECORD
