Metadata-Version: 2.4
Name: pubmedquery
Version: 0.1.13
Summary: A Python package to download data from PubMed
Author: Yeshwant Chillakuru
Requires-Python: >=3.8
Requires-Dist: numpy
Requires-Dist: pandas
Requires-Dist: requests
Dynamic: author
Dynamic: description
Dynamic: requires-dist
Dynamic: requires-python
Dynamic: summary
